l6e_forge_cli/__init__.py
l6e_forge_cli/chat.py
l6e_forge_cli/create.py
l6e_forge_cli/dev.py
l6e_forge_cli/main.py
l6e_forge_cli/memory.py
l6e_forge_cli/models.py
l6e_forge_cli/package.py
l6e_forge_cli/template.py
l6e_forge_cli/templates/__init__.py
l6e_forge_cli/templates/agent_assistant_basic_py.py
l6e_forge_cli/templates/agent_assistant_model_py.py
l6e_forge_cli/templates/agent_echo_py.py
l6e_forge_cli/templates/agent_ollama_py.py
l6e_forge_cli/templates/config_toml.py
l6e_forge_cli/templates/providers/base.py
l6e_forge_cli/templates/providers/lmstudio.py
l6e_forge_cli/templates/providers/ollama.py
l6e_forge_cli/templates/specs.py
l6e_forge_cli-0.1.0.dist-info/LICENSE
l6e_forge_cli-0.1.0.dist-info/METADATA
l6e_forge_cli-0.1.0.dist-info/WHEEL
l6e_forge_cli-0.1.0.dist-info/entry_points.txt
l6e_forge_cli-0.1.0.dist-info/RECORD
